djangorestql/__init__.py
djangorestql/exceptions.py
djangorestql/fields.py
djangorestql/filters.py
djangorestql/mixins.py
djangorestql/operations.py
djangorestql/parser.py
djangorestql/serializers.py
djangorestql/settings.py
djangorestql-1.0.1.dist-info/METADATA
djangorestql-1.0.1.dist-info/WHEEL
djangorestql-1.0.1.dist-info/top_level.txt
djangorestql-1.0.1.dist-info/RECORD
