Metadata-Version: 2.1
Name: djangorestql
Version: 1.0.1
Summary: UNKNOWN
Home-page: UNKNOWN
Author: Ohunayo Gege
Author-email: ohunayogege@gmail.com
License: MIT
Platform: UNKNOWN
Classifier: License :: OSI Approved :: MIT License
Classifier: Programming Language :: Python :: 3
Classifier: Programming Language :: Python :: 3.8
